isub
