Metadata-Version: 1.1
Name: isub
Version: 0.1.6
Summary: A utility CLI for TORQUE, a portable batch system
Home-page: https://bitbucket.org/kmiya/isub
Author: Kohei Miyaguchi
Author-email: quote.curly@gmail.com
License: UNKNOWN
Platform: UNKNOWN
Classifier: Environment :: Console
Classifier: Intended Audience :: Developers
Classifier: Operating System :: OS Independent
Classifier: Programming Language :: Python
Classifier: Topic :: Utilities
